perfting.setuptools-1.1.2-py3.9-nspkg.pth
perfting/setuptools/__init__.py
perfting/setuptools/attriclass.py
perfting/setuptools/extension.py
perfting/setuptools/package.py
perfting/setuptools/py.typed
perfting.setuptools-1.1.2.dist-info/LICENSE
perfting.setuptools-1.1.2.dist-info/METADATA
perfting.setuptools-1.1.2.dist-info/WHEEL
perfting.setuptools-1.1.2.dist-info/namespace_packages.txt
perfting.setuptools-1.1.2.dist-info/top_level.txt
perfting.setuptools-1.1.2.dist-info/RECORD
